ansible/module_utils/network/solace/__init__.py
ansible/module_utils/network/solace/solace_cloud_utils.py
ansible/module_utils/network/solace/solace_common.py
ansible/module_utils/network/solace/solace_utils.py
ansible/modules/network/solace/solace_acl_client_connect_exception.py
ansible/modules/network/solace/solace_acl_profile.py
ansible/modules/network/solace/solace_acl_publish_topic_exception.py
ansible/modules/network/solace/solace_acl_subscribe_topic_exception.py
ansible/modules/network/solace/solace_bridge.py
ansible/modules/network/solace/solace_bridge_remote_subscription.py
ansible/modules/network/solace/solace_bridge_remote_vpn.py
ansible/modules/network/solace/solace_bridge_tls_cn.py
ansible/modules/network/solace/solace_cert_authority.py
ansible/modules/network/solace/solace_client_profile.py
ansible/modules/network/solace/solace_client_username.py
ansible/modules/network/solace/solace_cloud_account_gather_facts.py
ansible/modules/network/solace/solace_cloud_get_facts.py
ansible/modules/network/solace/solace_cloud_get_service.py
ansible/modules/network/solace/solace_cloud_service.py
ansible/modules/network/solace/solace_dmr_bridge.py
ansible/modules/network/solace/solace_dmr_cluster.py
ansible/modules/network/solace/solace_dmr_cluster_link.py
ansible/modules/network/solace/solace_dmr_cluster_link_remote_address.py
ansible/modules/network/solace/solace_dmr_cluster_link_trusted_cn.py
ansible/modules/network/solace/solace_gather_facts.py
ansible/modules/network/solace/solace_get_available.py
ansible/modules/network/solace/solace_get_bridge_remote_vpns.py
ansible/modules/network/solace/solace_get_bridges.py
ansible/modules/network/solace/solace_get_client_profiles.py
ansible/modules/network/solace/solace_get_client_usernames.py
ansible/modules/network/solace/solace_get_facts.py
ansible/modules/network/solace/solace_get_magic_queues.py
ansible/modules/network/solace/solace_get_mqtt_session_subscriptions.py
ansible_solace-0.7.8.dist-info/LICENSE
ansible_solace-0.7.8.dist-info/METADATA
ansible_solace-0.7.8.dist-info/WHEEL
ansible_solace-0.7.8.dist-info/top_level.txt
ansible_solace-0.7.8.dist-info/RECORD
