Metadata-Version: 2.1
Name: ansible-solace
Version: 0.7.8
Summary: Ansible modules to configure Solace PubSub+ event brokers with SEMP.
Home-page: https://github.com/solace-iot-team/ansible-solace
Author: Solace Corporation
Author-email: ricardo.gomez-ulmke@solace.com
License: MIT License
Project-URL: Source, https://github.com/solace-iot-team/ansible-solace-modules
Project-URL: Tracker, https://github.com/solace-iot-team/ansible-solace-modules/issues
Keywords: solace semp ansible pubsub+
Platform: UNKNOWN
Classifier: Development Status :: 3 - Alpha
Classifier: Intended Audience :: Developers
Classifier: Programming Language :: Python :: 3
Classifier: License :: OSI Approved :: MIT License
Classifier: Operating System :: OS Independent
Classifier: Topic :: System :: Networking
Requires-Python: >=3.6
Requires-Dist: requests (>=2.24.0)
Requires-Dist: xmltodict (>=0.12.0)
